Metadata-Version: 1.0
Name: crowdED
Version: 0.1.3
Summary: This package contains the methods to generate simulated workers and tasks of a crowdsourcing use case
Home-page: https://github.com/MaastrichtU-IDS/crowdED
Author: Pedro V Hernandez Serrano
Author-email: p.hernandezserrano@maastrichtuniversity.nl
License: MIT
Platform: UNKNOWN
